{
  "assets/css/backend.css": "assets/css/backend-22807d1304.css",
  "assets/css/frontend.css": "assets/css/frontend-a1b2f87080.css",
  "assets/css/media-manager.css": "assets/css/media-manager-9cc3013770.css",
  "assets/fonts/icomoon.svg": "assets/fonts/icomoon-669ef5005d.svg",
  "assets/fonts/icomoon.ttf": "assets/fonts/icomoon-b7cc673a78.ttf",
  "assets/fonts/icomoon.woff": "assets/fonts/icomoon-45535ea5a6.woff",
  "assets/js/app.js": "assets/js/app-7565142b23.js",
  "assets/js/frontend.js": "assets/js/frontend-f5814b797f.js",
  "assets/js/vendor.js": "assets/js/vendor-6ae20ee748.js"
}